{
  "captured_at": "2026-07-24T01:21:10.979027+00:00",
  "modifiers": {
    "gold_pass_boost_pct": 0,
    "events": []
  },
  "accounts": [
    {
      "tag": "#8P88Q0GLQ",
      "name": "the dark LORD",
      "town_hall": 17,
      "offense_completion_pct": 84.8,
      "rush_risk": 11.2,
      "rush_band": "slightly rushed",
      "build_days_to_finish": 1319.2,
      "trophies": 62,
      "war_stars": 566,
      "guide_mode": "time_to_max",
      "next_up": "Barbarian King"
    }
  ],
  "gold_pass_season": {
    "source": "api",
    "season_start": "2026-07-01 08:00:00+00:00",
    "season_end": "2026-08-01 08:00:00+00:00",
    "ends_in": "8d 6h",
    "active": true
  },
  "scheduled_events": [
    {
      "event": "Season reset",
      "estimate": false,
      "active": false,
      "starts_in": "8d 6h"
    },
    {
      "event": "Clan Games",
      "estimate": true,
      "active": true,
      "ends_in": "4d 6h"
    },
    {
      "event": "CWL",
      "estimate": true,
      "active": false,
      "starts_in": "8d 6h"
    },
    {
      "event": "Raid Weekend",
      "estimate": true,
      "active": true,
      "ends_in": "3d 5h"
    }
  ]
}